setup.cfg
setup.py
json_to_relation/__init__.py
json_to_relation/col_data_type.py
json_to_relation/edxTrackLogJSONParser.py
json_to_relation/fixSequenceIDs.py
json_to_relation/generic_json_parser.py
json_to_relation/input_source.py
json_to_relation/json_to_relation.py
json_to_relation/locationManager.py
json_to_relation/modulestoreImporter.py
json_to_relation/mongodb.py
json_to_relation/mysqldb.py
json_to_relation/output_disposition.py
json_to_relation/test_course_id_extraction.py
json_to_relation/utils.py
json_to_relation.egg-info/PKG-INFO
json_to_relation.egg-info/SOURCES.txt
json_to_relation.egg-info/dependency_links.txt
json_to_relation.egg-info/requires.txt
json_to_relation.egg-info/top_level.txt
json_to_relation/test/__init__.py
json_to_relation/test/testAddAnonToActivityGradeTable.py
json_to_relation/test/testModuleStoreImporter.py
json_to_relation/test/test_edxTrackLogJSONParser.py
json_to_relation/test/test_json_to_relation.py
json_to_relation/test/test_mongodb.py
json_to_relation/test/test_utils.py
scripts/__init__.py
scripts/addAnonToActivityGradeTable.py
scripts/addAnonToUserGradeTable.py
scripts/cronRefreshUserCountryTable.py
scripts/json2sql.py
scripts/lookupOpenEdxHash.py
scripts/makeAnonScreenName.py
scripts/manageEdxDb.py
scripts/printUnbuffered.py
scripts/testAllTruthFiles.py