Metadata-Version: 1.0
Name: json-to-relation
Version: 0.4
Summary: Converts file with multiple JSON objects to one relational table.
Home-page: https://github.com/paepcke/json_to_relation
Author: Andreas Paepcke
Author-email: paepcke@cs.stanford.edu
License: BSD
Keywords: json,relation,OpenEdX
Platform: UNKNOWN
